ports/__init__.py
PortsPy-0.2.2.dist-info/METADATA
PortsPy-0.2.2.dist-info/WHEEL
PortsPy-0.2.2.dist-info/top_level.txt
PortsPy-0.2.2.dist-info/RECORD
