Metadata-Version: 2.1
Name: PortsPy
Version: 0.2.2
Summary: Modern Webserver
Home-page: http://github.com/Ehnryu/ports
Author: Ehnryu/Sakurai07
Author-email: blzzardst0rm@gmail.com
License: MIT
Keywords: webserver,ports
Platform: UNKNOWN
Classifier: Programming Language :: Python :: 3
